LICENSE
pymec_lp.py
setup.py
math_econ_code.egg-info/PKG-INFO
math_econ_code.egg-info/SOURCES.txt
math_econ_code.egg-info/dependency_links.txt
math_econ_code.egg-info/top_level.txt