Metadata-Version: 2.1
Name: math-econ-code
Version: 0.1
Summary: description of the package
Home-page: 
Author-email: ag133@nyu.edu
License: GNU
Platform: UNKNOWN
Requires-Python: >= 3
License-File: LICENSE
